Supplychain/Generic/__init__.py
Supplychain/Generic/adt_writer.py
Supplychain/Generic/adx_and_file_writer.py
Supplychain/Generic/adx_wrapper.py
Supplychain/Generic/cosmo_api_parameters.py
Supplychain/Generic/csv_folder_reader.py
Supplychain/Generic/csv_folder_writer.py
Supplychain/Generic/duration.py
Supplychain/Generic/excel_folder_reader.py
Supplychain/Generic/excel_folder_writer.py
Supplychain/Generic/folder_io.py
Supplychain/Generic/json_folder_reader.py
Supplychain/Generic/json_folder_writer.py
Supplychain/Generic/memory_folder_io.py
Supplychain/Generic/simulator_io.py
Supplychain/Generic/storage_queue_writer.py
Supplychain/Generic/timer.py
Supplychain/Generic/util.py
Supplychain/Protocol/__init__.py
Supplychain/Protocol/cmaes_optimization_algorithm.py
Supplychain/Protocol/default_transformation.py
Supplychain/Protocol/multiprocessing_optimization.py
Supplychain/Protocol/objective_functions.py
Supplychain/Protocol/protocol.py
Supplychain/Run/__init__.py
Supplychain/Run/cmaes_optimization.py
Supplychain/Run/consumers.py
Supplychain/Run/dataset_helpers.py
Supplychain/Run/decision_variables.py
Supplychain/Run/helpers.py
Supplychain/Run/local_sensitivity_analysis_comets.py
Supplychain/Run/simulation.py
Supplychain/Run/simulation_comets.py
Supplychain/Run/stochastic_optimization.py
Supplychain/Run/uncertainty_analysis.py
Supplychain/Run/uncertainty_analysis_comets.py
Supplychain/Run/uncertainty_analysis_helper_functions.py
Supplychain/Run/uncertainty_specs.py
Supplychain/Schema/__init__.py
Supplychain/Schema/adt_column_description.py
Supplychain/Schema/default_values.py
Supplychain/Schema/modifications.py
Supplychain/Schema/numeric_attributes.py
Supplychain/Schema/simulator_files_description.py
Supplychain/Schema/statistics.py
Supplychain/Schema/validation_schemas.py
Supplychain/Transform/__init__.py
Supplychain/Transform/complete_dict.py
Supplychain/Transform/from_dict_to_simulator.py
Supplychain/Transform/from_dict_to_table.py
cosmotech_supplychain-6.4.1.dist-info/licenses/LICENSE
cosmotech_supplychain-6.4.1.dist-info/METADATA
cosmotech_supplychain-6.4.1.dist-info/WHEEL
cosmotech_supplychain-6.4.1.dist-info/top_level.txt
cosmotech_supplychain-6.4.1.dist-info/RECORD
