Metadata-Version: 2.4
Name: CosmoTech-SupplyChain
Version: 6.4.1
Summary: A support package for Cosmotech SupplyChain
Author-email: Cosmo Tech <platform@cosmotech.com>
Project-URL: Homepage, https://www.cosmotech.com
Project-URL: Source, https://github.com/Cosmo-Tech/supplychain-python-library
License-File: LICENSE
Requires-Dist: azure-core~=1.36.0
Requires-Dist: azure-digitaltwins-core~=1.2.0
Requires-Dist: azure-identity~=1.16.1
Requires-Dist: azure-kusto-data~=4.4.1
Requires-Dist: azure-kusto-ingest~=4.4.1
Requires-Dist: azure-storage-queue~=12.14.0
Requires-Dist: azure-storage-blob~=12.27.0
Requires-Dist: CosmoTech-Acceleration-Library~=0.10.2
Requires-Dist: cosmotech-run-orchestrator~=2.0.2
Requires-Dist: comets~=1.5.2
Requires-Dist: cma>=4.4.0
Requires-Dist: jsonschema>=4.21.1
Requires-Dist: numpy>=2.3.4
Requires-Dist: openpyxl>=3.1.5
Requires-Dist: pandas>=2.3.3
Requires-Dist: python-dateutil>=2.9.0
Requires-Dist: pytest>=8.4.2
Dynamic: license-file
